demo_awscdk_construct/__init__.py
demo_awscdk_construct/py.typed
demo_awscdk_construct/_jsii/__init__.py
demo_awscdk_construct/_jsii/demo-awscdk-construct@0.0.5.jsii.tgz
demo_awscdk_construct-0.0.5.dist-info/LICENSE
demo_awscdk_construct-0.0.5.dist-info/METADATA
demo_awscdk_construct-0.0.5.dist-info/WHEEL
demo_awscdk_construct-0.0.5.dist-info/top_level.txt
demo_awscdk_construct-0.0.5.dist-info/RECORD
