Metadata-Version: 2.1
Name: demo-awscdk-construct
Version: 0.0.5
Summary: demo-awscdk-construct
Home-page: https://github.com/hustshawn/my-ecs-quickstart-construct.git
Author: hustshawn<hustshawn@gmail.com>
License: Apache-2.0
Project-URL: Source, https://github.com/hustshawn/my-ecs-quickstart-construct.git
Classifier: Intended Audience :: Developers
Classifier: Operating System :: OS Independent
Classifier: Programming Language :: JavaScript
Classifier: Programming Language :: Python :: 3 :: Only
Classifier: Programming Language :: Python :: 3.8
Classifier: Programming Language :: Python :: 3.9
Classifier: Programming Language :: Python :: 3.10
Classifier: Programming Language :: Python :: 3.11
Classifier: Typing :: Typed
Classifier: Development Status :: 5 - Production/Stable
Classifier: License :: OSI Approved
Requires-Python: ~=3.8
License-File: LICENSE
Requires-Dist: aws-cdk-lib <3.0.0,>=2.114.1
Requires-Dist: constructs <11.0.0,>=10.0.5
Requires-Dist: jsii <2.0.0,>=1.93.0
Requires-Dist: publication >=0.0.3
Requires-Dist: typeguard ~=2.13.3
